<?xml version="1.0" encoding="UTF-8"?>
<DARoots Version="1" Minor="26">
  <FileSet Name="sources_1" Type="DesignSrcs" RelSrcDir="$PSRCDIR/sources_1">
    <Filter Type="EDIFSrcs"/>
    <File Path="$PPRDIR/../fpga_impl.ngc">
      <FileInfo>
        <Attr Name="UsedInSynthesis" Val="1"/>
        <Attr Name="UsedInImplementation" Val="1"/>
      </FileInfo>
    </File>
    <File Path="$PPRDIR/../toplevel.ngc">
      <FileInfo>
        <Attr Name="UsedInSynthesis" Val="1"/>
        <Attr Name="UsedInImplementation" Val="1"/>
      </FileInfo>
    </File>
    <File Path="$PPRDIR/../sub_bytes.ngc">
      <FileInfo>
        <Attr Name="UsedInSynthesis" Val="1"/>
        <Attr Name="UsedInImplementation" Val="1"/>
      </FileInfo>
    </File>
    <File Path="$PPRDIR/../rol_mod.ngc">
      <FileInfo>
        <Attr Name="UsedInSynthesis" Val="1"/>
        <Attr Name="UsedInImplementation" Val="1"/>
      </FileInfo>
    </File>
    <File Path="$PPRDIR/../pt_buffer.ngc">
      <FileInfo>
        <Attr Name="UsedInSynthesis" Val="1"/>
        <Attr Name="UsedInImplementation" Val="1"/>
      </FileInfo>
    </File>
    <File Path="$PPRDIR/../mix_columns.ngc">
      <FileInfo>
        <Attr Name="UsedInSynthesis" Val="1"/>
        <Attr Name="UsedInImplementation" Val="1"/>
      </FileInfo>
    </File>
    <File Path="$PPRDIR/../main.ngc">
      <FileInfo>
        <Attr Name="UsedInSynthesis" Val="1"/>
        <Attr Name="UsedInImplementation" Val="1"/>
      </FileInfo>
    </File>
    <File Path="$PPRDIR/../key_expansion.ngc">
      <FileInfo>
        <Attr Name="UsedInSynthesis" Val="1"/>
        <Attr Name="UsedInImplementation" Val="1"/>
      </FileInfo>
    </File>
    <File Path="$PPRDIR/../aes_round.ngc">
      <FileInfo>
        <Attr Name="UsedInSynthesis" Val="1"/>
        <Attr Name="UsedInImplementation" Val="1"/>
      </FileInfo>
    </File>
    <File Path="$PPRDIR/../aes_full.ngc">
      <FileInfo>
        <Attr Name="UsedInSynthesis" Val="1"/>
        <Attr Name="UsedInImplementation" Val="1"/>
      </FileInfo>
    </File>
    <Config>
      <Option Name="DesignMode" Val="GateLvl"/>
      <Option Name="GateLvlMode" Val="EDIF"/>
      <Option Name="TopFile" Val="$PPRDIR/../fpga_impl.ngc"/>
      <Option Name="TopAutoSet" Val="TRUE"/>
    </Config>
  </FileSet>
</DARoots>
